gequests/__init__.py
gequests/frequest.py
gequests-2.28.1.dist-info/METADATA
gequests-2.28.1.dist-info/WHEEL
gequests-2.28.1.dist-info/top_level.txt
gequests-2.28.1.dist-info/RECORD
